[
  {
"userName": "Ahmet Yasin Uzun",
"destination": "Karamürsel iottech",
"purpose": "Konteyner Boşaltma",
"projectCode": "entity.aserwq",
"cost": "1879",
"startDate": "2010-12-01",
"endDate": "2012-05-07"

},
{
"userName": "Sefa Çakır",
"destination": "Karabük iottech",
"purpose": "Server Bakım",
"projectCode": "entity.aserwq",
"cost": "10000",
"startDate": "2008-12-01",
"endDate": "2012-09-07"


},
{

"userName": "Adem Ali",
"destination": "Zonguldak iottech",
"purpose": "Kurulum",
"projectCode": "entity.aserwq",
"cost": "20000",
"startDate": "2011-12-01",
"endDate": "2018-05-07"

},
{

"userName": "Yusuf Muaz",
"destination": "Manisa Maden İşletme",
"purpose": "Kontrol",
"projectCode": "entity.aserwq",
"cost": "20174",
"startDate": "2018-12-01",
"endDate": "2019-05-07"

}
]
